<item>
<title>MSNBC Live Streaming</title>
<link>https://watch.livenewson.com/u1nGj51te137bKp1FAFfDg==,1549684802/LS-ATL-54548-10/index.m3u8</link>
<thumbnail>https://www.livenewsnow.com/wp-content/uploads/2014/11/MSNBC-1-238x178.jpg</thumbnail>
<Fanart>https://image.tmdb.org/t/p/w780/wqtaHWOEZ3rXDJ8c6ZZShulbo18.jpg</Fanart>
<synop>Seasoned musician Jackson Maine discovers — and falls in love with — struggling artist Ally. She has just about given up on her dream to make it big as a singer — until Jack coaxes her into the spotlight. But even as Ally&#x27;s career takes off, the personal side of their relationship is breaking down, as Jack fights an ongoing battle with his own internal demons.</synop>
<imdb></imdb>
</item>
	
	
