   <item>
      <title>match of the day week 24</title>
      <link>
	  <sublink> https://vd40.mycdn.me/?expires=1516725273160&srcIp=207.237.67.138&srcAg=CHROME_ANDROID&type=3&sig=501aa903414b94fc44d19ed424cc7c2e01fb69df&ct=0&urls=5.61.22.77&clientType=0&id=349041265254(part 1)</sublink>
	   <sublink>https://vd35.mycdn.me/?expires=1516725704635&srcIp=207.237.67.138&srcAg=CHROME_ANDROID&type=3&sig=3e0a739b2e495ab6521f5046b61d75c313bb91d6&ct=0&urls=217.20.145.49&clientType=0&id=349047622246(part 2)</sublink>
	  </link>
      <thumbnail>http://www.fullmatchesandshows.com/wp-content/uploads/2017/02/MOTDdddd.jpg</thumbnail>
    </item>
	
	 <item>
      <title>MOTD 2 week 24</title>
	  <link>
      <sublink>https://vd69.mycdn.me/?expires=1516725817554&srcIp=207.237.67.138&srcAg=CHROME_ANDROID&type=3&sig=c2bbf338a29855c948857aefeb2bc0325536c5ce&ct=0&urls=217.20.145.46&clientType=0&id=349423929958(part 1)</sublink>
	  <sublink>https://vd67.mycdn.me/?expires=1516726006119&srcIp=207.237.67.138&srcAg=CHROME_ANDROID&type=3&sig=b396630d94f9fefdd67591196b19aff5a6f5e886&ct=0&urls=217.20.145.45&clientType=0&id=349425568358(part 2)</sublink>
	  </link>
      <thumbnail>https://highlightsandshows.com/wp-content/uploads/2016/12/motd-2.jpg</thumbnail>
    </item>
	
	<item>
      <title>southampton-vs-tottenham-hotspur-highlights</title>
      <link>https://vd70.mycdn.me/?expires=1516726184439&srcIp=207.237.67.138&srcAg=CHROME_ANDROID&type=3&sig=c1ef6db2f9d612d66ee96642543c8de3d1aa8bb9&ct=0&urls=217.20.153.75&clientType=0&id=349423340134</link>
      <thumbnail>http://www.fullmatchesandshows.com/wp-content/uploads/2018/01/Southampton-vs-Tottenham-Hotspur.jpg</thumbnail>
    </item>

	
	<item>
      <title></title>
      <link></link>
      <thumbnail></thumbnail>
    </item>
	
	<item>
      <title></title>
      <link>https://cf-b2.streamablevideo.com/video/mp4/7own4.mp4?token=1515880447-8huqw%2Fr7EZQis5bnxqu8Li%2FMx4PsJx0TlO</link>
      <thumbnail></thumbnail>
    </item>