	<item>
      <title>Detroit Pistons vs New Orleans Pelicans</title>
	  <link>http://gg.notlive.xyz/nba_list/0021700841h.m3u8</link>
      <thumbnail>http://nbahdo.com/wp-content/uploads/2017/03/Detroit-Pistons-vs-New-Orleans-Pelicans-01.jpg</thumbnail>
    </item>
	
	 <item>
      <title>Philadelphia 76ers vs New York Knicks</title>
	  <link>http://gg.notlive.xyz/nba_list/0021700842h.m3u8</link>
      <thumbnail>http://nbahdo.com/wp-content/uploads/2017/03/Philadelphia-76ers-vs-New-York-Knicks-25.jpg</thumbnail>
    </item>
	
	 <item>
      <title>la clippers vs brooklyn nets</title>
	  <link>http://gg.notlive.xyz/nba_list/0021700843h.m3u8</link>
      <thumbnail>https://i.axs.com/2017/08/la-clippers-vs-brooklyn-nets-tickets_03-04-18_17_59a72cd26335e.png</thumbnail>
    </item>
	
	 <item>
      <title>Orlando Magic v Chicago Bulls</title>
	  <link>http://gg.notlive.xyz/nba_list/0021700844h.m3u8</link>
      <thumbnail>http://www.chicagonow.com/bulls-bloc/files/2014/11/Bulls-vs.-Magic.jpg</thumbnail>
    </item>
	